{
  "collectionName": "components_blocks_heroes",
  "info": {
    "displayName": "Hero",
    "icon": "crown",
    "description": "Large heading with optional subheading, image and call to action"
  },
  "options": {},
  "attributes": {
    "heading": {
      "type": "string",
      "required": true
    },
    "subheading": {
      "type": "text"
    },
    "image": {
      "type": "media",
      "multiple": false,
      "required": false,
      "allowedTypes": ["images"]
    },
    "ctaLabel": {
      "type": "string"
    },
    "ctaHref": {
      "type": "string"
    }
  }
}
